.coveragerc
.gitignore
.travis.yml
LICENSE
README.md
requirements.txt
runtests.py
setup.py
tox.ini
denorm/__init__.py
denorm/daemon.py
denorm/denorms.py
denorm/dependencies.py
denorm/fields.py
denorm/helpers.py
denorm/middleware.py
denorm/models.py
denorm/db/__init__.py
denorm/db/base.py
denorm/db/mysql/__init__.py
denorm/db/mysql/triggers.py
denorm/db/postgresql/__init__.py
denorm/db/postgresql/triggers.py
denorm/db/sqlite3/__init__.py
denorm/db/sqlite3/triggers.py
denorm/management/__init__.py
denorm/management/commands/__init__.py
denorm/management/commands/denorm_daemon.py
denorm/management/commands/denorm_drop.py
denorm/management/commands/denorm_flush.py
denorm/management/commands/denorm_init.py
denorm/management/commands/denorm_rebuild.py
denorm/management/commands/denorm_sql.py
denorm/management/commands/denormalize.py
denorm/migrations/0001_initial.py
denorm/migrations/__init__.py
denorm/south_migrations/0001_initial.py
denorm/south_migrations/0002_auto__chg_field_dirtyinstance_object_id.py
denorm/south_migrations/__init__.py
django_denorm.egg-info/PKG-INFO
django_denorm.egg-info/SOURCES.txt
django_denorm.egg-info/dependency_links.txt
django_denorm.egg-info/requires.txt
django_denorm.egg-info/top_level.txt
docs/.gitignore
docs/Makefile
docs/conf.py
docs/index.rst
docs/reference.rst
docs/tutorial.rst
test_denorm_project/manage.py
test_denorm_project/test_app/__init__.py
test_denorm_project/test_app/models.py
test_denorm_project/test_app/tests.py
test_denorm_project/test_app/views.py
test_denorm_project/test_app/migrations/0001_initial.py
test_denorm_project/test_app/migrations/0002_auto_20151014_1049.py
test_denorm_project/test_app/migrations/0003_auto_20160218_1341.py
test_denorm_project/test_app/migrations/0004_auto_20160306_1822.py
test_denorm_project/test_app/migrations/__init__.py
test_denorm_project/test_denorm_project/__init__.py
test_denorm_project/test_denorm_project/settings.py
test_denorm_project/test_denorm_project/settings_mysql.py
test_denorm_project/test_denorm_project/settings_postgis.py
test_denorm_project/test_denorm_project/settings_postgres.py
test_denorm_project/test_denorm_project/settings_sqlite.py
