Metadata-Version: 1.1
Name: django-denorm
Version: 1.0.0
Summary: Denormalization magic for Django
Home-page: http://github.com/django-denorm/django-denorm/
Author: Christian Schilling <initcrash@gmail.com>, James Turnbull <james@incuna.com>, Petr Dlouhy <petr.dlouhy@email.cz>
Author-email: django-denorm@googlegroups.com
License: UNKNOWN
Download-URL: http://github.com/django-denorm/django-denorm/downloads
Platform: UNKNOWN
Classifier: Development Status :: 2 - Pre-Alpha
Classifier: Framework :: Django
Classifier: Intended Audience :: Developers
Classifier: Intended Audience :: System Administrators
Classifier: Operating System :: OS Independent
Classifier: Topic :: Software Development
